AO/__init__.py
AO/addition.py
AO/division.py
AO/multiplication.py
AO/subtraction.py
test/__init__.py
test/test_addition.py
test/test_division.py
test/test_multiplication.py
test/test_subtraction.py
Aritmeticoperations-0.1.1.dist-info/METADATA
Aritmeticoperations-0.1.1.dist-info/WHEEL
Aritmeticoperations-0.1.1.dist-info/top_level.txt
Aritmeticoperations-0.1.1.dist-info/RECORD
