Metadata-Version: 2.1
Name: Aritmeticoperations
Version: 0.1.1
Summary: A package for operations functions
Home-page: https://github.com/Akhilkumargolla/arithmeticoperations
Author: AkhilKumarGolla
Author-email: akhilkumar.golla@outlook.com
License: MIT
Classifier: Development Status :: 3 - Alpha
Classifier: License :: OSI Approved :: MIT License
Classifier: Programming Language :: Python :: 3
Classifier: Programming Language :: Python :: 3.9
Classifier: Programming Language :: Python :: 3.10
Classifier: Programming Language :: Python :: 3.11
Classifier: Programming Language :: Python :: 3.12
